htping/__init__.py
htping/cli.py
htping/helpers.py
htping-0.1.0.dist-info/AUTHORS.rst
htping-0.1.0.dist-info/LICENSE
htping-0.1.0.dist-info/METADATA
htping-0.1.0.dist-info/WHEEL
htping-0.1.0.dist-info/entry_points.txt
htping-0.1.0.dist-info/top_level.txt
htping-0.1.0.dist-info/RECORD
