Metadata-Version: 2.1
Name: htping
Version: 0.1.0
Summary: CLI tool to ping sites and return HTTP status codes
Home-page: https://github.com/ttafsir/htping
Author: Tafsir Thiam
Author-email: ttafsir@gmail.com
License: MIT license
Keywords: htping
Platform: UNKNOWN
Classifier: Development Status :: 2 - Pre-Alpha
Classifier: Intended Audience :: Developers
Classifier: License :: OSI Approved :: MIT License
Classifier: Natural Language :: English
Classifier: Programming Language :: Python :: 3
Classifier: Programming Language :: Python :: 3.7
Classifier: Programming Language :: Python :: 3.8
Classifier: Programming Language :: Python :: 3.9
Requires-Python: >=3.5
Requires-Dist: Click (>=7.0)
Requires-Dist: requests (>=2.25)
Requires-Dist: colorama (>=0.4)
